{
  "name": "UnArchiver",
  "identifier": "com.ssalonen.unarchiver.source",
  "sourceURL": "https://raw.githubusercontent.com/ssalonen/unarchiver/main/altstore-source.json",
  "apps": [
    {
      "name": "UnArchiver",
      "bundleIdentifier": "com.yourcompany.unarchiver",
      "developerName": "ssalonen",
      "subtitle": "Open TAR, GZip, ZIP, XZ archives",
      "localizedDescription": "View files inside TAR, GZip, BZip2, XZ, and ZIP archives directly on your iPhone.\n\nSupported formats:\n\u2022 .tar.gz / .tgz\n\u2022 .tar.bz2 / .tbz2\n\u2022 .tar.xz / .txz\n\u2022 .tar\n\u2022 .gz\n\u2022 .zip\n\nFeatures:\n\u2022 Opens directly from Files app and any share sheet\n\u2022 Built-in text viewer for source code, JSON, logs\n\u2022 Search within files\n\u2022 Share / export individual files",
      "iconURL": "https://raw.githubusercontent.com/ssalonen/unarchiver/main/icon.png",
      "tintColor": "007AFF",
      "category": "utilities",
      "version": "2.1.11",
      "versionDate": "2026-04-19T18:53:24+00:00",
      "versionDescription": "See GitHub release notes.",
      "downloadURL": "https://github.com/ssalonen/unarchiver/releases/download/v2.1.11/UnArchiver.ipa",
      "size": 1123590,
      "versions": [
        {
          "version": "2.1.11",
          "date": "2026-04-19T18:53:24+00:00",
          "localizedDescription": "See GitHub release notes.",
          "downloadURL": "https://github.com/ssalonen/unarchiver/releases/download/v2.1.11/UnArchiver.ipa",
          "size": 1123590,
          "minOSVersion": "17.0"
        },
        {
          "version": "2.1.10",
          "date": "2026-04-19T17:48:38+00:00",
          "localizedDescription": "See GitHub release notes.",
          "downloadURL": "https://github.com/ssalonen/unarchiver/releases/download/v2.1.10/UnArchiver.ipa",
          "size": 1123169,
          "minOSVersion": "17.0"
        },
        {
          "version": "2.1.9",
          "date": "2026-04-19T15:37:38+00:00",
          "localizedDescription": "See GitHub release notes.",
          "downloadURL": "https://github.com/ssalonen/unarchiver/releases/download/v2.1.9/UnArchiver.ipa",
          "size": 1117623,
          "minOSVersion": "17.0"
        },
        {
          "version": "2.1.8",
          "date": "2026-04-19T15:09:40+00:00",
          "localizedDescription": "See GitHub release notes.",
          "downloadURL": "https://github.com/ssalonen/unarchiver/releases/download/v2.1.8/UnArchiver.ipa",
          "size": 1122135,
          "minOSVersion": "17.0"
        },
        {
          "version": "2.1.7",
          "date": "2026-04-19T14:29:34+00:00",
          "localizedDescription": "See GitHub release notes.",
          "downloadURL": "https://github.com/ssalonen/unarchiver/releases/download/v2.1.7/UnArchiver.ipa",
          "size": 1118092,
          "minOSVersion": "17.0"
        },
        {
          "version": "2.1.6",
          "date": "2026-04-19T12:19:24+00:00",
          "localizedDescription": "See GitHub release notes.",
          "downloadURL": "https://github.com/ssalonen/unarchiver/releases/download/v2.1.6/UnArchiver.ipa",
          "size": 1052501,
          "minOSVersion": "17.0"
        },
        {
          "version": "2.1.5",
          "date": "2026-04-19T12:00:45+00:00",
          "localizedDescription": "See GitHub release notes.",
          "downloadURL": "https://github.com/ssalonen/unarchiver/releases/download/v2.1.5/UnArchiver.ipa",
          "size": 1052498,
          "minOSVersion": "17.0"
        },
        {
          "version": "2.1.4",
          "date": "2026-04-19T10:10:21+00:00",
          "localizedDescription": "See GitHub release notes.",
          "downloadURL": "https://github.com/ssalonen/unarchiver/releases/download/v2.1.4/UnArchiver.ipa",
          "size": 1046151,
          "minOSVersion": "17.0"
        },
        {
          "version": "2.1.3",
          "date": "2026-04-19T08:59:30+00:00",
          "localizedDescription": "See GitHub release notes.",
          "downloadURL": "https://github.com/ssalonen/unarchiver/releases/download/v2.1.3/UnArchiver.ipa",
          "size": 1046212,
          "minOSVersion": "17.0"
        },
        {
          "version": "2.1.2",
          "date": "2026-04-19T07:53:07+00:00",
          "localizedDescription": "See GitHub release notes.",
          "downloadURL": "https://github.com/ssalonen/unarchiver/releases/download/v2.1.2/UnArchiver.ipa",
          "size": 1045350,
          "minOSVersion": "17.0"
        },
        {
          "version": "2.0.2",
          "date": "2026-04-18T19:07:42+00:00",
          "localizedDescription": "See GitHub release notes.",
          "downloadURL": "https://github.com/ssalonen/unarchiver/releases/download/v2.0.2/UnArchiver.ipa",
          "size": 1045215,
          "minOSVersion": "17.0"
        },
        {
          "version": "1.10",
          "date": "2026-04-18T09:29:45+00:00",
          "localizedDescription": "See GitHub release notes.",
          "downloadURL": "https://github.com/ssalonen/unarchiver/releases/download/v1.10/UnArchiver.ipa",
          "size": 948280,
          "minOSVersion": "17.0"
        },
        {
          "version": "1.9",
          "date": "2026-04-18T09:02:49+00:00",
          "localizedDescription": "See GitHub release notes.",
          "downloadURL": "https://github.com/ssalonen/unarchiver/releases/download/v1.9/UnArchiver.ipa",
          "size": 946786,
          "minOSVersion": "17.0"
        },
        {
          "version": "1.8",
          "date": "2026-04-18T05:46:46+00:00",
          "localizedDescription": "See GitHub release notes.",
          "downloadURL": "https://github.com/ssalonen/unarchiver/releases/download/v1.8/UnArchiver.ipa",
          "size": 943611,
          "minOSVersion": "17.0"
        },
        {
          "version": "1.7",
          "date": "2026-04-18T04:23:05+00:00",
          "localizedDescription": "See GitHub release notes.",
          "downloadURL": "https://github.com/ssalonen/unarchiver/releases/download/v1.7/UnArchiver.ipa",
          "size": 944806,
          "minOSVersion": "17.0"
        },
        {
          "version": "1.6",
          "date": "2026-04-17T20:35:52+00:00",
          "localizedDescription": "See GitHub release notes.",
          "downloadURL": "https://github.com/ssalonen/unarchiver/releases/download/v1.6/UnArchiver.ipa",
          "size": 944784,
          "minOSVersion": "17.0"
        }
      ]
    }
  ],
  "news": []
}
